CHANGELOG.md
LICENSE
MANIFEST.in
README.md
setup.cfg
setup.py
pip_services3_elasticsearch/__init__.py
pip_services3_elasticsearch.egg-info/PKG-INFO
pip_services3_elasticsearch.egg-info/SOURCES.txt
pip_services3_elasticsearch.egg-info/dependency_links.txt
pip_services3_elasticsearch.egg-info/requires.txt
pip_services3_elasticsearch.egg-info/top_level.txt
pip_services3_elasticsearch.egg-info/zip-safe
pip_services3_elasticsearch/build/DefaultElasticSearchFactory.py
pip_services3_elasticsearch/build/__init__.py
pip_services3_elasticsearch/log/ElasticSearchLogger.py
pip_services3_elasticsearch/log/__init__.py
test/fixtures/LoggerFixture.py
test/fixtures/__init__.py
test/log/__init__.py
test/log/test_ElasticSearchLogger.py